site_config/__init__.py
site_config/backends/__init__.py
site_config/backends/model_backend/__init__.py
site_config/backends/model_backend/admin.py
site_config/backends/model_backend/forms.py
site_config/backends/model_backend/models.py
site_config/backends/settings_backend/__init__.py
site_config/backends/settings_backend/models.py
site_config/choices.py
site_config/context_processors.py
site_config/decorators.py
site_config/models.py
site_config/registry.py
site_config/templates/admin/site_config/application/change_form.html
site_config/templates/admin/site_config/website/change_form.html
site_config/templates/site_config/curtained.html
site_config/tests/__init__.py
site_config/tests/lib.py
site_config/tests/test_config_register.py
site_config/tests/test_context_processors.py
site_config/tests/test_decorators.py
site_config/tests/test_modelbackend_admin.py
site_config/tests/test_modelbackend_basic_usage.py
site_config/tests/test_settingsbackend_basic_usage.py
site_config/tests/test_utils.py
site_config/utils.py
site_config-2.0.1.dist-info/WHEEL
site_config-2.0.1.dist-info/METADATA
site_config-2.0.1.dist-info/RECORD
