Metadata-Version: 2.1
Name: site-config
Version: 2.0.1
Summary: Django configuration Utility to manage multiple "websites" in a project.
Home-page: https://github.com/ImaginaryLandscape/django_site_config
License: BSD
Author: Imagescape
Author-email: info@imagescape.com
Requires-Python: >=3.7,<4.0
Classifier: License :: Other/Proprietary License
Classifier: Programming Language :: Python :: 3
Classifier: Programming Language :: Python :: 3.7
Classifier: Programming Language :: Python :: 3.8
Classifier: Programming Language :: Python :: 3.9
Requires-Dist: django (>=3.2,<4.0)
